the_odds_api_sdk/__init__.py
the_odds_api_sdk/client.py
the_odds_api_sdk/exceptions.py
the_odds_api_sdk/models.py
the_odds_api_sdk-1.0.1.dist-info/licenses/LICENSE
the_odds_api_sdk-1.0.1.dist-info/METADATA
the_odds_api_sdk-1.0.1.dist-info/WHEEL
the_odds_api_sdk-1.0.1.dist-info/top_level.txt
the_odds_api_sdk-1.0.1.dist-info/RECORD
