Metadata-Version: 2.4
Name: the-odds-api-sdk
Version: 1.0.1
Summary: Unofficial Python SDK for The Odds API
Author-email: "Christian J. Starr" <christianjstarr@icloud.com>
License: MIT
Project-URL: Homepage, https://github.com/ChristianJStarr/the-odds-api-sdk-python
Project-URL: Documentation, https://the-odds-api.com/liveapi/guides/v4/
Project-URL: Repository, https://github.com/ChristianJStarr/the-odds-api-sdk-python.git
Project-URL: Bug Tracker, https://github.com/ChristianJStarr/the-odds-api-sdk-python/issues
Keywords: odds,sports,betting,api,sdk
Classifier: Development Status :: 5 - Production/Stable
Classifier: Intended Audience :: Developers
Classifier: License :: OSI Approved :: MIT License
Classifier: Operating System :: OS Independent
Classifier: Programming Language :: Python :: 3
Classifier: Programming Language :: Python :: 3.7
Classifier: Programming Language :: Python :: 3.8
Classifier: Programming Language :: Python :: 3.9
Classifier: Programming Language :: Python :: 3.10
Classifier: Programming Language :: Python :: 3.11
Classifier: Programming Language :: Python :: 3.12
Requires-Python: >=3.7
License-File: LICENSE
Requires-Dist: requests>=2.25.0
Requires-Dist: typing-extensions>=4.0.0; python_version < "3.8"
Provides-Extra: dev
Requires-Dist: pytest>=7.0.0; extra == "dev"
Requires-Dist: pytest-cov>=4.0.0; extra == "dev"
Requires-Dist: black>=22.0.0; extra == "dev"
Requires-Dist: flake8>=5.0.0; extra == "dev"
Requires-Dist: mypy>=1.0.0; extra == "dev"
Requires-Dist: isort>=5.10.0; extra == "dev"
Dynamic: license-file
